LICENSE
MANIFEST.in
README.txt
setup.py
quickplot/__init__.py
quickplot/plot.py
quickplot/utils.py
quickplot.egg-info/PKG-INFO
quickplot.egg-info/SOURCES.txt
quickplot.egg-info/dependency_links.txt
quickplot.egg-info/requires.txt
quickplot.egg-info/top_level.txt