Metadata-Version: 1.1
Name: quickplot
Version: 0.1.2
Summary: The batteries-included plotting wrapper for matplotlib
Home-page: https://github.com/ksheedlo/quickplot
Author: Ken Sheedlo
Author-email: ovrkenthousand@gmail.com
License: UNKNOWN
Download-URL: https://github.com/ksheedlo/quickplot/archive/master.zip
Platform: UNKNOWN
Classifier: Development Status :: 3 - Alpha
Classifier: Intended Audience :: Science/Research
Classifier: License :: OSI Approved :: MIT License
Classifier: Operating System :: OS Independent
Classifier: Programming Language :: Python
Classifier: Programming Language :: Python :: 2
Classifier: Programming Language :: Python :: 3
Classifier: Topic :: Scientific/Engineering :: Visualization
